[ {
  "key" : "general",
  "concerns" : [ {
    "name" : "TODOs",
    "filesCount" : 1,
    "linesOfCode" : 174,
    "numberOfRegexLineMatches" : 2,
    "fileCountPerExtension" : [ {
      "name" : "  *.ts",
      "value" : 1,
      "description" : [ ]
    } ],
    "linesOfCodePerExtension" : [ {
      "name" : "  *.ts",
      "value" : 174,
      "description" : [ ]
    } ]
  }, {
    "name" : "Unclassified",
    "filesCount" : 139,
    "linesOfCode" : 8944,
    "numberOfRegexLineMatches" : 0,
    "fileCountPerExtension" : [ {
      "name" : "  *.ts",
      "value" : 79,
      "description" : [ ]
    }, {
      "name" : "  *.tsx",
      "value" : 54,
      "description" : [ ]
    }, {
      "name" : "  *.css",
      "value" : 1,
      "description" : [ ]
    }, {
      "name" : "  *.mjs",
      "value" : 3,
      "description" : [ ]
    }, {
      "name" : "  *.py",
      "value" : 1,
      "description" : [ ]
    }, {
      "name" : "  *.js",
      "value" : 1,
      "description" : [ ]
    } ],
    "linesOfCodePerExtension" : [ {
      "name" : "  *.ts",
      "value" : 4527,
      "description" : [ ]
    }, {
      "name" : "  *.tsx",
      "value" : 4235,
      "description" : [ ]
    }, {
      "name" : "  *.css",
      "value" : 105,
      "description" : [ ]
    }, {
      "name" : "  *.mjs",
      "value" : 37,
      "description" : [ ]
    }, {
      "name" : "  *.py",
      "value" : 36,
      "description" : [ ]
    }, {
      "name" : "  *.js",
      "value" : 4,
      "description" : [ ]
    } ]
  } ],
  "concernsGroup" : null,
  "fileCountPerConcern" : [ {
    "name" : "TODOs",
    "value" : 1,
    "description" : [ ]
  }, {
    "name" : "Unclassified",
    "value" : 139,
    "description" : [ ]
  } ],
  "linesOfCodePerConcern" : [ {
    "name" : "TODOs",
    "value" : 174,
    "description" : [ ]
  }, {
    "name" : "Unclassified",
    "value" : 8944,
    "description" : [ ]
  } ]
} ]